aishengsai/0通用的TensorFlow训练模型代码.py
aishengsai/1-1虚假职位描述.py
aishengsai/10正哥.py
aishengsai/111.py
aishengsai/1预测新客户违约风险.py
aishengsai/21-1-数据分析和挖掘.py
aishengsai/22-1-将开源的数据生成代码中需要的格式.py
aishengsai/22-2-Gemma-2B-Lora微调.py
aishengsai/22-3-chartgpt.py
aishengsai/22-3-chartgpt1.py
aishengsai/22-3-智能自动驾驶.py
aishengsai/22-3-智能自动驾驶1.py
aishengsai/22-模型微调-情感分析-1.py
aishengsai/22-模型微调-情感分析.py
aishengsai/2大模型根据特定任务微调.py
aishengsai/3智能自动驾驶场景-PyTorch.py
aishengsai/3智能自动驾驶场景-TensorFlow.py
aishengsai/__init__.py
aishengsai/亚伟-first.py
aishengsai/亚伟-test.py
aishengsai/亚伟-third.py
aishengsai/引入库.py
aishengsai/正哥build.py
aishengsai/正哥carBrand.py
aishengsai/正哥no1.py
aishengsai/base/1字符串拼接和判断.py
aishengsai/base/2循环.py
aishengsai/base/3函数.py
aishengsai/base/4数据容器.py
aishengsai/base/5.循环操作列表.py
aishengsai/base/6.字典.py
aishengsai/base/7文件操作.py
aishengsai/base/8.1异常处理和包、模块、功能引用.py
aishengsai/base/first.py
aishengsai/base/second.py
aishengsai/base/test.py
aishengsai/base/my_package/__init__.py
aishengsai/base/my_package/my_module1.py
aishengsai/base/my_package/my_module2.py
aishengsai/base/my_utils/__init__.py
aishengsai/base/my_utils/file_util.py
aishengsai/base/my_utils/str_util.py
aishengsai-0.0.9.dist-info/LICENSE
aishengsai-0.0.9.dist-info/METADATA
aishengsai-0.0.9.dist-info/WHEEL
aishengsai-0.0.9.dist-info/top_level.txt
aishengsai-0.0.9.dist-info/RECORD
