Metadata-Version: 2.1
Name: aishengsai
Version: 0.0.9
Summary: 为了方便省赛使用
Author-email: aresen <aresenyang@163.com>
Classifier: Programming Language :: Python :: 3
Classifier: License :: OSI Approved :: MIT License
Classifier: Operating System :: OS Independent
Requires-Python: >=3.7
License-File: LICENSE
